MANIFEST.in
NEWS.txt
README.rst
setup.py
deepsee/__init__.py
deepsee.egg-info/PKG-INFO
deepsee.egg-info/SOURCES.txt
deepsee.egg-info/dependency_links.txt
deepsee.egg-info/entry_points.txt
deepsee.egg-info/not-zip-safe
deepsee.egg-info/top_level.txt