Metadata-Version: 1.0
Name: deepsee
Version: 0.1
Summary: Dependency aware processing framework.
Home-page: UNKNOWN
Author: Francois Lagunas
Author-email: francois.lagunas@gmail.com
License: MIT
Platform: UNKNOWN
